kozax/genetic_programming.py
kozax/environments/SR_environments/fitzhugh_nagumo.py
kozax/environments/SR_environments/lorenz_attractor.py
kozax/environments/SR_environments/lotka_volterra.py
kozax/environments/SR_environments/time_series_environment_base.py
kozax/environments/SR_environments/vd_pol_oscillator.py
kozax/environments/control_environments/acrobot.py
kozax/environments/control_environments/cart_pole.py
kozax/environments/control_environments/control_environment_base.py
kozax/environments/control_environments/harmonic_oscillator.py
kozax/environments/control_environments/reactor.py
kozax/fitness_functions/Gymnax_fitness_function.py
kozax/fitness_functions/ODE_fitness_function.py
kozax/fitness_functions/SR_fitness_function.py
kozax/fitness_functions/base_fitness_function.py
kozax/genetic_operators/crossover.py
kozax/genetic_operators/initialization.py
kozax/genetic_operators/mutation.py
kozax/genetic_operators/reproduction.py
kozax-0.0.11.dist-info/METADATA
kozax-0.0.11.dist-info/WHEEL
kozax-0.0.11.dist-info/licenses/LICENSE.md
kozax-0.0.11.dist-info/RECORD
