Metadata-Version: 2.4
Name: kozax
Version: 0.0.11
Summary: Genetic programming library in JAX.
Author-email: Sigur de Vries <sigur@hotmail.nl>
License: kozax: Genetic programming framework in JAX
License-File: LICENSE.md
Keywords: Evolutionary algorithms,Genetic programming,JAX,Symbolic regression
Classifier: Development Status :: 3 - Alpha
Classifier: Intended Audience :: Developers
Classifier: Natural Language :: English
Classifier: Programming Language :: Python :: 3
Classifier: Topic :: Scientific/Engineering :: Artificial Intelligence
Requires-Python: >=3.10
Requires-Dist: jax>=0.4.36
Requires-Dist: optax>=0.2.3
Requires-Dist: sympy>=1.13.3
